pylistic/__init__.py
pylistic/dict_list.py
pylistic/list_list.py
pylistic/pylistic.py
pylistic-0.0.1.dist-info/METADATA
pylistic-0.0.1.dist-info/WHEEL
pylistic-0.0.1.dist-info/top_level.txt
pylistic-0.0.1.dist-info/RECORD
