Metadata-Version: 2.1
Name: pylistic
Version: 0.0.1
Summary: A python package to handle lists
Home-page: UNKNOWN
Author: Gabriel Caldas
Author-email: gabrielgcbs97@gmail.com
License: UNKNOWN
Keywords: python,list,data structure
Platform: UNKNOWN
Classifier: Development Status :: 3 - Alpha
Classifier: Intended Audience :: Developers
Classifier: Programming Language :: Python :: 3
Classifier: Operating System :: MacOS :: MacOS X
Classifier: Operating System :: Microsoft :: Windows
Classifier: Operating System :: POSIX :: Linux
